threadtools/__init__.py
threadtools/connection.py
threadtools/globals.py
threadtools/lock.py
threadtools/py.typed
threadtools/signal.py
threadtools-1.0.2.dist-info/licenses/LICENSE
threadtools-1.0.2.dist-info/METADATA
threadtools-1.0.2.dist-info/WHEEL
threadtools-1.0.2.dist-info/top_level.txt
threadtools-1.0.2.dist-info/RECORD
