Metadata-Version: 2.4
Name: threadtools
Version: 1.0.2
Summary: Tools for synchronizing threads using better locks and signals.
Author-email: Drew Whitney <drewlwhitney@gmail.com>
License-Expression: GPL-3.0-or-later
Project-URL: Homepage, https://github.com/drewlwhitney/threadtools
Project-URL: Issues, https://github.com/drewlwhitney/threadtools/issues
Requires-Python: >=3.13
License-File: LICENSE
Dynamic: license-file
